ergo_python_appkit/ErgoBox.py
ergo_python_appkit/ErgoContractBase.py
ergo_python_appkit/ErgoTransaction.py
ergo_python_appkit/__init__.py
ergo_python_appkit/appkit.py
ergo_python_appkit/jars/ergo-appkit-5.0.0.jar
ergo_python_appkit/typings/java-stubs/__init__.pyi
ergo_python_appkit/typings/java-stubs/applet/__init__.pyi
ergo_python_appkit/typings/java-stubs/awt/__init__.pyi
ergo_python_appkit/typings/java-stubs/awt/color/__init__.pyi
ergo_python_appkit/typings/java-stubs/awt/datatransfer/__init__.pyi
ergo_python_appkit/typings/java-stubs/awt/desktop/__init__.pyi
ergo_python_appkit/typings/java-stubs/awt/dnd/__init__.pyi
ergo_python_appkit/typings/java-stubs/awt/dnd/peer/__init__.pyi
ergo_python_appkit/typings/java-stubs/awt/event/__init__.pyi
ergo_python_appkit/typings/java-stubs/awt/font/__init__.pyi
ergo_python_appkit/typings/java-stubs/awt/geom/__init__.pyi
ergo_python_appkit/typings/java-stubs/awt/im/__init__.pyi
ergo_python_appkit/typings/java-stubs/awt/im/spi/__init__.pyi
ergo_python_appkit/typings/java-stubs/awt/image/__init__.pyi
ergo_python_appkit/typings/java-stubs/awt/image/renderable/__init__.pyi
ergo_python_appkit/typings/java-stubs/awt/peer/__init__.pyi
ergo_python_appkit/typings/java-stubs/awt/print_/__init__.pyi
ergo_python_appkit/typings/java-stubs/beans/__init__.pyi
ergo_python_appkit/typings/java-stubs/beans/beancontext/__init__.pyi
ergo_python_appkit/typings/java-stubs/io/__init__.pyi
ergo_python_appkit/typings/java-stubs/lang/__init__.pyi
ergo_python_appkit/typings/java-stubs/lang/annotation/__init__.pyi
ergo_python_appkit/typings/java-stubs/lang/instrument/__init__.pyi
ergo_python_appkit/typings/java-stubs/lang/invoke/__init__.pyi
ergo_python_appkit/typings/java-stubs/lang/management/__init__.pyi
ergo_python_appkit/typings/java-stubs/lang/module/__init__.pyi
ergo_python_appkit/typings/java-stubs/lang/ref/__init__.pyi
ergo_python_appkit/typings/java-stubs/lang/reflect/__init__.pyi
ergo_python_appkit/typings/java-stubs/math/__init__.pyi
ergo_python_appkit-0.3.2.dist-info/LICENSE
ergo_python_appkit-0.3.2.dist-info/METADATA
ergo_python_appkit-0.3.2.dist-info/WHEEL
ergo_python_appkit-0.3.2.dist-info/top_level.txt
ergo_python_appkit-0.3.2.dist-info/RECORD
