Metadata-Version: 2.1
Name: ergo-python-appkit
Version: 0.3.2
Summary: A python wrapper for the Ergo Appkit
Home-page: https://github.com/ergo-pad/ergo-python-appkit
Author: Robert Pieter van Leeuwen
Author-email: luivatra@gmail.com
Classifier: Programming Language :: Python :: 3
Classifier: License :: OSI Approved :: MIT License
Classifier: Operating System :: OS Independent
License-File: LICENSE
